{
  "info": {
    "description": "data",
    "version": "1.0",
    "year": 2025,
    "contributor": "search engine",
    "source": "no_augmentation",
    "license": {
      "name": "Creative Commons Attribution 4.0 International",
      "url": "https://creativecommons.org/licenses/by/4.0/"
    },
    "leaf_info": {
      "leaf_number": "OCT_559.0"
    }
  },
  "images": [
    {
      "id": 1636931445,
      "width": 256,
      "height": 256,
      "file_name": "image (224).JPG",
      "size": 13903,
      "format": "JPG",
      "url": "",
      "hash": "",
      "status": "success",
      "original_filename": "CREC_HLB 6791.JPG",
      "pvc_filename": "1cd61f76-358f-40ff-8d67-ac61c575fbc1___CREC_HLB 6791.JPG"
    }
  ],
  "annotations": [
    {
      "id": 5422514454,
      "image_id": 1636931445,
      "category_id": 2000000015,
      "segmentation": [],
      "area": 35435,
      "bbox": [
        0,
        5,
        256,
        251
      ]
    },
    {
      "id": 2438138454,
      "image_id": 1636931445,
      "category_id": 2000000015,
      "segmentation": [],
      "area": 217,
      "bbox": [
        111,
        175,
        18,
        18
      ]
    },
    {
      "id": 6931837454,
      "image_id": 1636931445,
      "category_id": 2000000015,
      "segmentation": [],
      "area": 108,
      "bbox": [
        0,
        36,
        16,
        24
      ]
    }
  ],
  "categories": [
    {
      "id": 2000000015,
      "name": "Haunglongbing_(Citrus_greening)",
      "supercategory": "Orange"
    }
  ]
}