{
  "info": {
    "description": "data",
    "version": "1.0",
    "year": 2025,
    "contributor": "search engine",
    "source": "no_augmentation",
    "license": {
      "name": "Creative Commons Attribution 4.0 International",
      "url": "https://creativecommons.org/licenses/by/4.0/"
    },
    "leaf_info": {
      "leaf_number": "OCT_241.0"
    }
  },
  "images": [
    {
      "id": 6185698077,
      "width": 256,
      "height": 256,
      "file_name": "image (5036).JPG",
      "size": 18051,
      "format": "JPG",
      "url": "",
      "hash": "",
      "status": "success",
      "original_filename": "CREC_HLB 4837.JPG",
      "pvc_filename": "eb0b5272-30bf-44b0-92c3-a2f97bbaf563___CREC_HLB 4837.JPG"
    }
  ],
  "annotations": [
    {
      "id": 8160914085,
      "image_id": 6185698077,
      "category_id": 2000000015,
      "segmentation": [],
      "area": 56832,
      "bbox": [
        0,
        0,
        256,
        256
      ]
    },
    {
      "id": 1061441085,
      "image_id": 6185698077,
      "category_id": 2000000015,
      "segmentation": [],
      "area": 174,
      "bbox": [
        0,
        128,
        16,
        16
      ]
    }
  ],
  "categories": [
    {
      "id": 2000000015,
      "name": "Haunglongbing_(Citrus_greening)",
      "supercategory": "Orange"
    }
  ]
}