{
  "info": {
    "description": "data",
    "version": "1.0",
    "year": 2025,
    "contributor": "search engine",
    "source": "augmented",
    "license": {
      "name": "Creative Commons Attribution 4.0 International",
      "url": "https://creativecommons.org/licenses/by/4.0/"
    }
  },
  "images": [
    {
      "id": 5369175412,
      "width": 256,
      "height": 256,
      "file_name": "image (124).JPG",
      "size": 14041,
      "format": "JPG",
      "url": "",
      "hash": "",
      "status": "success"
    }
  ],
  "annotations": [
    {
      "id": 5939019413,
      "image_id": 5369175412,
      "category_id": 1000000015,
      "segmentation": [],
      "area": 23792,
      "bbox": [
        45,
        16,
        169,
        223
      ]
    }
  ],
  "categories": [
    {
      "id": 1000000015,
      "name": "Haunglongbing_(Citrus_greening)",
      "supercategory": "Orange"
    }
  ]
}