{
  "info": {
    "description": "data",
    "version": "1.0",
    "year": 2025,
    "contributor": "search engine",
    "source": "augmented",
    "license": {
      "name": "Creative Commons Attribution 4.0 International",
      "url": "https://creativecommons.org/licenses/by/4.0/"
    }
  },
  "images": [
    {
      "id": 5224832181,
      "width": 256,
      "height": 256,
      "file_name": "image (4781).JPG",
      "size": 8540,
      "format": "JPG",
      "url": "",
      "hash": "",
      "status": "success"
    }
  ],
  "annotations": [
    {
      "id": 1970431182,
      "image_id": 5224832181,
      "category_id": 1000000015,
      "segmentation": [],
      "area": 13836,
      "bbox": [
        17,
        9,
        141,
        237
      ]
    },
    {
      "id": 1770454182,
      "image_id": 5224832181,
      "category_id": 1000000015,
      "segmentation": [],
      "area": 315,
      "bbox": [
        106,
        50,
        37,
        15
      ]
    }
  ],
  "categories": [
    {
      "id": 1000000015,
      "name": "Haunglongbing_(Citrus_greening)",
      "supercategory": "Orange"
    }
  ]
}