{
  "info": {
    "description": "data",
    "version": "1.0",
    "year": 2025,
    "contributor": "search engine",
    "source": "augmented",
    "license": {
      "name": "Creative Commons Attribution 4.0 International",
      "url": "https://creativecommons.org/licenses/by/4.0/"
    }
  },
  "images": [
    {
      "id": 8831823451,
      "width": 256,
      "height": 256,
      "file_name": "image (4214).JPG",
      "size": 15029,
      "format": "JPG",
      "url": "",
      "hash": "",
      "status": "success"
    }
  ],
  "annotations": [
    {
      "id": 6312803452,
      "image_id": 8831823451,
      "category_id": 1000000015,
      "segmentation": [],
      "area": 45427,
      "bbox": [
        0,
        0,
        256,
        256
      ]
    },
    {
      "id": 5788323452,
      "image_id": 8831823451,
      "category_id": 1000000015,
      "segmentation": [],
      "area": 130,
      "bbox": [
        158,
        129,
        17,
        16
      ]
    }
  ],
  "categories": [
    {
      "id": 1000000015,
      "name": "Haunglongbing_(Citrus_greening)",
      "supercategory": "Orange"
    }
  ]
}