{
  "info": {
    "description": "data",
    "version": "1.0",
    "year": 2025,
    "contributor": "search engine",
    "source": "augmented",
    "license": {
      "name": "Creative Commons Attribution 4.0 International",
      "url": "https://creativecommons.org/licenses/by/4.0/"
    }
  },
  "images": [
    {
      "id": 7488462500,
      "width": 256,
      "height": 256,
      "file_name": "image (68).JPG",
      "size": 7563,
      "format": "JPG",
      "url": "",
      "hash": "",
      "status": "success"
    }
  ],
  "annotations": [
    {
      "id": 5271666502,
      "image_id": 7488462500,
      "category_id": 1000000015,
      "segmentation": [],
      "area": 7600,
      "bbox": [
        0,
        8,
        243,
        239
      ]
    },
    {
      "id": 8076306502,
      "image_id": 7488462500,
      "category_id": 1000000015,
      "segmentation": [],
      "area": 548,
      "bbox": [
        143,
        156,
        33,
        36
      ]
    },
    {
      "id": 6790017502,
      "image_id": 7488462500,
      "category_id": 1000000015,
      "segmentation": [],
      "area": 249,
      "bbox": [
        48,
        144,
        26,
        15
      ]
    },
    {
      "id": 4069739502,
      "image_id": 7488462500,
      "category_id": 1000000015,
      "segmentation": [],
      "area": 161,
      "bbox": [
        144,
        144,
        33,
        11
      ]
    },
    {
      "id": 8962408502,
      "image_id": 7488462500,
      "category_id": 1000000015,
      "segmentation": [],
      "area": 107,
      "bbox": [
        0,
        92,
        11,
        36
      ]
    },
    {
      "id": 8528734502,
      "image_id": 7488462500,
      "category_id": 1000000015,
      "segmentation": [],
      "area": 132,
      "bbox": [
        138,
        113,
        21,
        15
      ]
    },
    {
      "id": 8768706502,
      "image_id": 7488462500,
      "category_id": 1000000015,
      "segmentation": [],
      "area": 143,
      "bbox": [
        160,
        116,
        31,
        9
      ]
    },
    {
      "id": 7489874502,
      "image_id": 7488462500,
      "category_id": 1000000015,
      "segmentation": [],
      "area": 331,
      "bbox": [
        145,
        79,
        51,
        24
      ]
    }
  ],
  "categories": [
    {
      "id": 1000000015,
      "name": "Haunglongbing_(Citrus_greening)",
      "supercategory": "Orange"
    }
  ]
}