{
  "info": {
    "description": "data",
    "version": "1.0",
    "year": 2025,
    "contributor": "search engine",
    "source": "augmented",
    "license": {
      "name": "Creative Commons Attribution 4.0 International",
      "url": "https://creativecommons.org/licenses/by/4.0/"
    }
  },
  "images": [
    {
      "id": 4873474616,
      "width": 256,
      "height": 256,
      "file_name": "image (3661).JPG",
      "size": 15782,
      "format": "JPG",
      "url": "",
      "hash": "",
      "status": "success"
    }
  ],
  "annotations": [
    {
      "id": 6142711617,
      "image_id": 4873474616,
      "category_id": 1000000015,
      "segmentation": [],
      "area": 51789,
      "bbox": [
        0,
        0,
        256,
        256
      ]
    },
    {
      "id": 7094622617,
      "image_id": 4873474616,
      "category_id": 1000000015,
      "segmentation": [],
      "area": 479,
      "bbox": [
        131,
        175,
        43,
        17
      ]
    }
  ],
  "categories": [
    {
      "id": 1000000015,
      "name": "Haunglongbing_(Citrus_greening)",
      "supercategory": "Orange"
    }
  ]
}