{
  "info": {
    "description": "data",
    "version": "1.0",
    "year": 2025,
    "contributor": "search engine",
    "source": "no_augmentation",
    "license": {
      "name": "Creative Commons Attribution 4.0 International",
      "url": "https://creativecommons.org/licenses/by/4.0/"
    },
    "leaf_info": {
      "leaf_number": "OCT_630.0"
    }
  },
  "images": [
    {
      "id": 2558475775,
      "width": 256,
      "height": 256,
      "file_name": "image (1100).JPG",
      "size": 19172,
      "format": "JPG",
      "url": "",
      "hash": "",
      "status": "success",
      "original_filename": "CREC_HLB 7075.JPG",
      "pvc_filename": "7e4f0e30-6c80-4c39-bf79-7bcf55a93817___CREC_HLB 7075.JPG"
    }
  ],
  "annotations": [
    {
      "id": 6899591786,
      "image_id": 2558475775,
      "category_id": 2000000015,
      "segmentation": [],
      "area": 35010,
      "bbox": [
        0,
        0,
        216,
        250
      ]
    }
  ],
  "categories": [
    {
      "id": 2000000015,
      "name": "Haunglongbing_(Citrus_greening)",
      "supercategory": "Orange"
    }
  ]
}