{
  "info": {
    "description": "data",
    "version": "1.0",
    "year": 2025,
    "contributor": "search engine",
    "source": "no_augmentation",
    "license": {
      "name": "Creative Commons Attribution 4.0 International",
      "url": "https://creativecommons.org/licenses/by/4.0/"
    },
    "leaf_info": {
      "leaf_number": "OCT_358.0"
    }
  },
  "images": [
    {
      "id": 9458672046,
      "width": 256,
      "height": 256,
      "file_name": "image (580).JPG",
      "size": 11458,
      "format": "JPG",
      "url": "",
      "hash": "",
      "status": "success",
      "original_filename": "CREC_HLB 5305.JPG",
      "pvc_filename": "4a3d6de2-a62d-4f1b-8a20-0536cde50fdd___CREC_HLB 5305.JPG"
    }
  ],
  "annotations": [
    {
      "id": 8635600056,
      "image_id": 9458672046,
      "category_id": 2000000015,
      "segmentation": [],
      "area": 29569,
      "bbox": [
        32,
        9,
        198,
        235
      ]
    }
  ],
  "categories": [
    {
      "id": 2000000015,
      "name": "Haunglongbing_(Citrus_greening)",
      "supercategory": "Orange"
    }
  ]
}