{
  "info": {
    "description": "data",
    "version": "1.0",
    "year": 2025,
    "contributor": "search engine",
    "source": "no_augmentation",
    "license": {
      "name": "Creative Commons Attribution 4.0 International",
      "url": "https://creativecommons.org/licenses/by/4.0/"
    },
    "leaf_info": {
      "leaf_number": "OCT_769.0"
    }
  },
  "images": [
    {
      "id": 1098173245,
      "width": 256,
      "height": 256,
      "file_name": "image (2696).JPG",
      "size": 9260,
      "format": "JPG",
      "url": "",
      "hash": "",
      "status": "success",
      "original_filename": "CREC_HLB 7640.JPG",
      "pvc_filename": "000945ae-3cf5-48c2-86a2-a3f1e777f2c7___CREC_HLB 7640.JPG"
    }
  ],
  "annotations": [
    {
      "id": 7080074253,
      "image_id": 1098173245,
      "category_id": 2000000015,
      "segmentation": [],
      "area": 14281,
      "bbox": [
        24,
        9,
        215,
        239
      ]
    }
  ],
  "categories": [
    {
      "id": 2000000015,
      "name": "Haunglongbing_(Citrus_greening)",
      "supercategory": "Orange"
    }
  ]
}