{
  "info": {
    "description": "data",
    "version": "1.0",
    "year": 2025,
    "contributor": "search engine",
    "source": "no_augmentation",
    "license": {
      "name": "Creative Commons Attribution 4.0 International",
      "url": "https://creativecommons.org/licenses/by/4.0/"
    },
    "leaf_info": {
      "leaf_number": "OCT_787.0"
    }
  },
  "images": [
    {
      "id": 6805386705,
      "width": 256,
      "height": 256,
      "file_name": "image (3859).JPG",
      "size": 14452,
      "format": "JPG",
      "url": "",
      "hash": "",
      "status": "success",
      "original_filename": "CREC_HLB 7712.JPG",
      "pvc_filename": "b1ab1fcb-5ec0-4931-9e35-58c1d464c682___CREC_HLB 7712.JPG"
    }
  ],
  "annotations": [
    {
      "id": 3435229712,
      "image_id": 6805386705,
      "category_id": 2000000015,
      "segmentation": [],
      "area": 35454,
      "bbox": [
        10,
        17,
        235,
        224
      ]
    }
  ],
  "categories": [
    {
      "id": 2000000015,
      "name": "Haunglongbing_(Citrus_greening)",
      "supercategory": "Orange"
    }
  ]
}